{
	"name": "TargetDataset2",
	"properties": {
		"linkedServiceName": {
			"referenceName": "linkedservicecopy",
			"type": "LinkedServiceReference"
		},
		"parameters": {
			"Filename": {
				"type": "string"
			}
		},
		"annotations": [],
		"type": "DelimitedText",
		"typeProperties": {
			"location": {
				"type": "AzureBlobStorageLocation",
				"fileName": {
					"value": "@dataset().Filename",
					"type": "Expression"
				},
				"folderPath": "Folder4",
				"container": "demo"
			},
			"columnDelimiter": ",",
			"escapeChar": "\\",
			"firstRowAsHeader": true,
			"quoteChar": "\""
		},
		"schema": []
	},
	"type": "Microsoft.DataFactory/factories/datasets"
}